pylistin/__init__.py
pylistin-1.0.1.dist-info/METADATA
pylistin-1.0.1.dist-info/WHEEL
pylistin-1.0.1.dist-info/top_level.txt
pylistin-1.0.1.dist-info/RECORD
