Metadata-Version: 2.1
Name: pylistin
Version: 1.0.1
Summary: Functions to work with list in python
Author-email: Camilo Barbosa <cab331@hotmail.com>
License: MIT
Project-URL: Homepage, https://github.com/calimpio/pylistin
Project-URL: Issues, https://github.com/calimpio/pylistin/issues
Classifier: Programming Language :: Python :: 3
Classifier: License :: OSI Approved :: MIT License
Classifier: Operating System :: OS Independent
Requires-Python: >=3.10.11
